[{
  "note": "起始畫面",
  "title": "翻開七十幾年前的報紙⋯",
  "image": "https://cdn.musou.tw/uploads/images/2760/9208ac5c-9f01-4d8d-b882-f858488f92c6.jpg",
  "image_caption": "圖片取自民報。上：1946/7/16；左下：1946/11/26；右下一：1946/4/6；右下二：1947/2/26",
  "description": "瀆職貪污不知恥、專賣局百鬼橫行。老羞成怒、可憐又可笑；警察開槍還亂打人，整個鄉村慘如戰場。",
  "address": "台灣",
  "lat": 23.797815,
  "lng": 121.000736,
  "zoom": 6,
  "prev_step_button": "上一站",
  "next_step_button": "下一站",
  "display_type": "default"
}, {
  "note": "第二站",
  "date": "1947/2/27",
  "title": "天馬茶房查緝私菸",
  "image": "https://i.imgur.com/VQF1dMJ.png",
  "image_license": "https://www.instagram.com/p/t7iV6EIbxl/",
  "description": "專賣局查緝員在天馬茶房前，查獲婦人林江邁在販賣私菸，查緝員欲沒收林婦全部的香菸及身上錢財。林婦表示生活困難苦苦哀求，圍觀民眾加入求情。但查緝員葉得根卻以手槍槍柄敲擊林婦頭部，導致流血昏迷。圍觀民眾憤怒擁上，查緝員棄車分頭逃逸。查緝員傅學通逃到永樂町開槍亂射，子彈擊中市民陳文溪，次日死亡。",
  "address": "天馬茶房",
  "lat": 25.0540749,
  "lng": 121.5119987,
  "zoom": 16,
  "prev_step_button": "上一站",
  "next_step_button": "下一站",
  "display_type": "default"
}, {
  "note": "第三站",
  "date": "1947/2/27",
  "title": "包圍警察總局",
  "image": "https://upload.wikimedia.org/wikipedia/commons/c/c7/2012-10-21_臺北市中山堂_臺北市政府警察局總局.jpg",
  "image_caption": "圖為警察總局原址。",
  "image_license": "Zengtuoying CC BY-SA 3.0",
  "description": "查緝員隨後逃到中山堂旁的警察總局。激憤群眾包圍警察總局，要求警方懲兇。\n\n民眾續包圍台北憲兵隊，要求交出兇手，憲兵團長張慕陶下令憲兵做出射擊姿勢，雙方交涉無結果，民眾在細雨中徹夜包圍到天亮。",
  "address": "警察總局",
  "lat": 25.0433839,
  "lng": 121.5093392,
  "zoom": 16,
  "prev_step_button": "上一站",
  "next_step_button": "下一站",
  "display_type": "default"
}, {
  "note": "第四站",
  "date": "1947/2/28",
  "title": "民報報導",
  "image": "https://cdn.musou.tw/uploads/images/2731/aa083ac3-9643-40ba-a196-793fd9290ad3.png",
  "description": "查緝私菸隊開槍擊斃賣烟婦人，群情昂奮要求賠醫藥費，竟肇起慘事。",
  "address": "御成町三丁目",
  "lat": 25.053279,
  "lng": 121.5221609,
  "zoom": 16,
  "prev_step_button": "上一站",
  "next_step_button": "下一站",
  "display_type": "default"
}, {
  "note": "第五站",
  "date": "1947/2/28",
  "title": "大稻埕罷工罷市",
  "image": "https://upload.wikimedia.org/wikipedia/commons/thumb/5/5b/李亭香餅舖.jpg/440px-李亭香餅舖.jpg",
  "image_license": "寺人孟子 CC BY-SA 4.0",
  "description": "由於不滿緝菸血案未獲解決，上午九點，民眾在街頭輪流演講，台北市民展開罷工、罷市，大小商店響應相繼關門，市民湧上街頭，尤其大稻埕更是人山人海、群情激昂。",
  "address": "大稻埕",
  "lat": 25.0550119,
  "lng": 121.5089476,
  "zoom": 14,
  "prev_step_button": "上一站",
  "next_step_button": "下一站",
  "display_type": "default"
}, {
  "note": "第六站",
  "date": "1947/2/28",
  "title": "民眾搗毀台北專賣局",
  "image": "https://cdn.musou.tw/uploads/images/2739/02064d4e-2892-4fb8-8c59-f0de6a708d8c.jpg",
  "description": "憤怒的市民衝入肇事查緝員所任職的專賣局臺北分局（今重慶南路上的彰化銀行臺北分行），毆打專賣局職員，搗毀辦公器具及玻璃，並將菸、酒、火柴、汽車等物搬出戶外焚毀。",
  "address": "台北專賣局",
  "lat": 25.0455928,
  "lng": 121.5132578,
  "zoom": 16,
  "prev_step_button": "上一站",
  "next_step_button": "下一站",
  "display_type": "default"
}, {
  "note": "第七站",
  "date": "1947/2/28",
  "title": "行政長官公署掃射",
  "description": "數千名群眾前往行政長官公署（今行政院）請願，沿途高呼「槍決犯人」，人潮由延平北路口蔓延到中山路口（今中山南、忠孝東路口）前。公署樓上衛兵立即開槍掃射。當場造成許多人死傷，民眾恐慌四處奔逃，使得情勢更加複雜，此為局勢惡化的關鍵。這種無差別射擊，激怒了更多民眾，戰後以來累積的新仇舊恨一起爆發。",
  "address": "行政長官公署",
  "lat": 25.0463125,
  "lng": 121.5211099,
  "zoom": 16,
  "prev_step_button": "上一站",
  "next_step_button": "下一站",
  "display_type": "default"
}, {
  "note": "第八站",
  "date": "1947/2/28",
  "title": "民眾佔領臺灣廣播電台號召反抗",
  "image": "https://cdn.musou.tw/uploads/images/2742/d3d8017f-0e57-4582-ba0c-e6c186c7ed43.jpg",
  "description": "台北城一片混亂，抗議民眾於新公園內開群眾大會，並佔領公園裡面的臺灣廣播電臺向全臺灣廣播，報導事件經過，並批判臺灣自戰後政治黑暗、貪污舞弊、民不聊生，並呼籲臺灣人與其餓死，不如起來反抗，驅逐各地貪官污吏以求生存。\n\n陳水扁市長任內將新公園改名為今日的「二二八和平紀念公園」、廣播電台也改為「台北市二二八紀念館」。",
  "address": "二二八紀念館",
  "lat": 25.0402394,
  "lng": 121.5156685,
  "zoom": 16,
  "prev_step_button": "上一站",
  "next_step_button": "下一站",
  "display_type": "default"
}, {
  "note": "第九站",
  "date": "1947/2/28",
  "title": "台北市臨時戒嚴",
  "image": "https://cdn.musou.tw/uploads/images/2728/bda885e7-38e2-4d49-bcec-7746eebe8885.jpg",
  "description": "警備總司令部發布臺北市臨時戒嚴令，派遣武裝軍警乘坐大卡車巡邏臺北市區，見到臺灣人的穿著打扮便開槍掃射。民眾再度包圍專賣總局、鐵路警察署、交通局等，並發生軍民衝突，許多民眾遭到射殺，一些詢問鐵路交通情形要回家的學生也遇害。",
  "address": "警備總司令部",
  "lat": 25.0463125,
  "lng": 121.5211099,
  "zoom": 11,
  "prev_step_button": "上一站",
  "next_step_button": "下一站",
  "display_type": "default"
}, {
  "note": "第十站",
  "date": "1947/3/1",
  "title": "陳儀廣播宣布全台戒嚴",
  "audio": "https://raw.githubusercontent.com/watchout-tw/watchout-plotdb/master/228/228.mp3",
  "description": "3月1日起，全臺灣各地先後知悉臺北的消息，事件蔓延全臺灣。陳儀廣播內文：台灣同胞昨天我宣布臨時戒嚴，我此刻以十二萬分的誠意，告訴最多數善良百姓，我之所以宣布戒嚴，完全是為了保護你們，你們千萬不要聽信奸人的謠言。有點疑惑、有點恐慌，對於守法的百姓絕對不多加傷害，你們千萬放心。",
  "address": "行政長官公署",
  "lat": 23.797815,
  "lng": 121.000736,
  "zoom": 6,
  "prev_step_button": "上一站",
  "next_step_button": "下一站",
  "display_type": "default"
}, {
  "note": "第十一站",
  "date": "1947/3/1",
  "title": "台北鐵路管理委員會",
  "image": "https://cdn.musou.tw/uploads/images/2744/a7edeaf3-a431-4a19-b2af-85d6fa0aea02.jpg",
  "description": "臺北市民眾包圍鐵路管理委員會（今鐵路局），警察大隊自樓上開槍掃射造成18死、40傷。",
  "address": "鐵道部",
  "lat": 25.0485365,
  "lng": 121.5109757,
  "zoom": 16,
  "prev_step_button": "上一站",
  "next_step_button": "下一站",
  "display_type": "default"
}, {
  "note": "第十二站",
  "date": "1947/3/1",
  "title": "台北市成立二二八處委會",
  "image": "https://cdn.musou.tw/uploads/images/2738/6255d492-9e94-4dd2-ba01-eda368c2e10a.jpg",
  "description": "臺北市參議會邀請國民大會代表、臺灣省參議員、國民參政會參政員，在中山堂成立「緝菸血案調查委員會」，後改為二二八事件處理委員會。",
  "address": "中山堂",
  "lat": 25.0433839,
  "lng": 121.5093392,
  "zoom": 15,
  "prev_step_button": "上一站",
  "next_step_button": "下一站",
  "display_type": "default"
}, {
  "note": "第十四站",
  "date": "1947/3/3",
  "title": "高雄要塞司令部等待出兵",
  "image": "https://upload.wikimedia.org/wikipedia/commons/thumb/f/f7/Peng_Mengji_%28cropped%29.jpg/210px-Peng_Mengji_%28cropped%29.jpg",
  "image_license": "Public Domain",
  "description": "事件蔓延全島，高雄市民包圍高雄市政府警察局，許多公務員退避至壽山的高雄要塞司令部。高雄要塞司令彭孟緝認為已經形同叛亂，並調整軍力布署以等待機會出兵。",
  "address": "高雄要塞",
  "lat": 22.6268696,
  "lng": 120.2737795,
  "zoom": 14,
  "prev_step_button": "上一站",
  "next_step_button": "下一站",
  "display_type": "default"
}, {
  "note": "第十五站",
  "date": "1947/3/4",
  "title": "高雄中學組成自衛隊",
  "image": "https://cdn.musou.tw/uploads/images/2749/843b5f13-0e4c-42c3-8700-cc66bd6fa14e.jpg",
  "description": "臺灣省立高雄第一中學原本是被群眾趁亂闖入，並計畫做為反抗政府的指揮中心。而部分學生不願學校遭到外人佔用，於3月4日組成雄中自衛隊，由李榮河（二排左三）和陳仁悲（二排左一）擔任正副隊長。後加入高雄工業職業學校、高雄商業職業學校、高雄第一女子中學學生，以軍訓用槍械維持學校附近治安，並將學校作為外省市民的收容所。",
  "address": "高雄中學",
  "lat": 22.6377741,
  "lng": 120.2975705,
  "zoom": 15,
  "prev_step_button": "上一站",
  "next_step_button": "下一站",
  "display_type": "default"
}, {
  "note": "第十六站",
  "date": "1947/3/5",
  "title": "高雄車站交戰",
  "image": "https://cdn.musou.tw/uploads/images/2750/ffe685d5-6bbf-46c2-91b7-fe5e55637de4.jpg",
  "description": "憲兵佔領高雄車站，並在二樓架設機槍不讓民眾接近，原本依賴鐵路運輸的糧食無法進入高雄，嚴重影響人民生計，於是雄中自衛隊另組決死隊，由陳仁悲擔任隊長，兵分三路進攻高雄車站驅逐駐紮車站的憲兵隊。但因火力差距懸殊，經歷五個小時交戰後撤離，雄中畢業生顏再策腹部中彈喪生。",
  "address": "高雄車站",
  "lat": 22.6395387,
  "lng": 120.3022948,
  "zoom": 16,
  "prev_step_button": "上一站",
  "next_step_button": "下一站",
  "display_type": "default"
}, {
  "note": "第十六･五站",
  "date": "1947/3/5",
  "title": "蔣介石回電報給陳儀表示已派兵",
  "image": "https://cdn.musou.tw/uploads/images/2733/4f061c68-4941-466c-8ba8-6aa6a172e776.jpg",
  "description": "蔣介石在南京回應陳儀派軍隊來台鎮壓的要求，並回函：「台灣陳長官。已派步兵一團并派憲兵一營，限本月七日由滬啓運，勿念。中正」",
  "address": "南京",
  "lat": 32.044261,
  "lng": 118.79732,
  "zoom": 12,
  "prev_step_button": "上一站",
  "next_step_button": "下一站",
  "display_type": "default"
}, {
  "note": "第十七站",
  "date": "1947/3/6",
  "title": "台中成立二七部隊",
  "image": "https://i.imgur.com/OuxvlMV.jpg",
  "image_caption": "二七部隊隊長鍾逸人，事件中被捕遭關押16年。",
  "description": "不同於處理委員會與其下保安委員會主張的議會民主路線，四百多名青年學生、地方民眾、泰雅族族人成立二七部隊，成員包含謝雪紅、鍾逸人、黃金島等多人所共同組織領導的反抗國民政府的武裝民兵，為當時規模最大、維持最久的反抗勢力組織。",
  "address": "台中干城",
  "lat": 24.1526328,
  "lng": 120.6335335,
  "zoom": 12,
  "prev_step_button": "上一站",
  "next_step_button": "下一站",
  "display_type": "default"
}, {
  "note": "第十八站",
  "date": "1947/3/8",
  "title": "基隆港軍隊登陸",
  "image": "https://image.peoplenews.tw/news/29b62f1e-d635-42ed-9a3f-5435bc0533f3.jpg",
  "image_license": "民報",
  "description": "包含楊亮功與劉雨卿領導的七千名兵力（第二十一師和憲兵第四團）在內的中國軍隊陸續抵達基隆，並有部隊在未靠岸前便以機槍掃射基隆。",
  "address": "基隆港",
  "lat": 25.15558,
  "lng": 121.7613347,
  "zoom": 14,
  "prev_step_button": "上一站",
  "next_step_button": "下一站",
  "display_type": "default"
}, {
  "note": "第十九站",
  "date": "1947/3/8",
  "title": "基隆大屠殺",
  "image": "https://cdn.musou.tw/uploads/images/2734/41d3526d-e4a1-48eb-a84b-41a7f4d6a0a5.jpg",
  "description": "基隆市宣布戒嚴，部隊四處搜捕民眾，沿途朝人群密集掃射，數百人被以鐵絲綑綁並推入海中處決。",
  "address": "基隆市",
  "lat": 25.1297953,
  "lng": 121.7420152,
  "zoom": 12,
  "prev_step_button": "上一站",
  "next_step_button": "下一站",
  "display_type": "default"
}, {
  "note": "第二十站",
  "date": "1947/3/8",
  "title": "中山堂攻擊事件",
  "image": "https://cdn.musou.tw/uploads/images/2738/6255d492-9e94-4dd2-ba01-eda368c2e10a.jpg",
  "description": "晚間，行政長官公署下令總攻擊，在中山堂處理委員會處理各部門事務的兩百多名青年學生遭軍隊殺害，開會者遭到逮捕或擊斃。",
  "address": "中山堂",
  "lat": 25.0433839,
  "lng": 121.5093392,
  "zoom": 16,
  "prev_step_button": "上一站",
  "next_step_button": "下一站",
  "display_type": "default"
}, {
  "note": "第二十一站",
  "title": "三月大屠殺開始",
  "description": "中華民國政府濫捕濫殺無辜臺灣人的「三月大屠殺」開始⋯\n\n二二八事件與隨後的三月大屠殺究竟造成多少傷亡，至今仍無法有定論。依據行政院1992年公布的《二二八事件研究報告》，整起事件中約有一萬八千至兩萬八千人死亡，其中包含許多當時政治、法律、醫學、學術、教育、藝術、媒體等各界的菁英。",
  "address": "台灣",
  "lat": 23.797815,
  "lng": 121.000736,
  "zoom": 6,
  "prev_step_button": "上一站",
  "next_step_button": "那些消失的台灣菁英⋯",
  "display_type": "default"
}]
